pash/__init__.py
pipeish/__init__.py
pipeish/commands.py
pipeish-0.3.0.dist-info/METADATA
pipeish-0.3.0.dist-info/RECORD
pipeish-0.3.0.dist-info/WHEEL
pipeish-0.3.0.dist-info/top_level.txt
psh/__init__.py
psh/commands.py
