Metadata-Version: 2.1
Name: pipeish
Version: 0.3.0
Summary: shell pipes and redirecting for python
Home-page: https://github.com/vigilancer/pipeish
Author: Andrey Elizarov
Author-email: vigilancer@example.com
License: WTFPL
Platform: UNKNOWN
Classifier: Programming Language :: Python :: 3
Classifier: License :: OSI Approved
Classifier: Operating System :: OS Independent
